mybackup/__init__.py
mybackup/cli.py
mybackup/core.py
mybackup/ui.py
mybackup/utils.py
mybackup-0.1.0.dist-info/licenses/LICENSE
mybackup-0.1.0.dist-info/METADATA
mybackup-0.1.0.dist-info/WHEEL
mybackup-0.1.0.dist-info/entry_points.txt
mybackup-0.1.0.dist-info/top_level.txt
mybackup-0.1.0.dist-info/RECORD
